{
  "placeholderImages": [
    {
      "id": "bride-avatar",
      "description": "Avatar for the bride",
      "imageUrl": "https://images.unsplash.com/photo-1677691256999-45d69a11b197?crop=entropy&cs=tinysrgb&fit=max&fm=jpg&ixid=M3w3NDE5ODJ8MHwxfHNlYXJjaHwxfHxicmlkZSUyMHBvcnRyYWl0fGVufDB8fHx8MTc3MTI0NjU5N3ww&ixlib=rb-4.1.0&q=80&w=1080",
      "imageHint": "bride portrait"
    },
    {
      "id": "registry-item-1",
      "description": "A beautiful dinnerware set",
      "imageUrl": "https://images.unsplash.com/photo-1758810741403-194444e8447f?crop=entropy&cs=tinysrgb&fit=max&fm=jpg&ixid=M3w3NDE5ODJ8MHwxfHNlYXJjaHw3fHxkaW5uZXJ3YXJlJTIwc2V0fGVufDB8fHx8MTc3MTI0NjU5N3ww&ixlib=rb-4.1.0&q=80&w=1080",
      "imageHint": "dinnerware set"
    },
    {
      "id": "registry-item-2",
      "description": "A high-quality stand mixer",
      "imageUrl": "https://images.unsplash.com/photo-1637571847531-1993f346426e?crop=entropy&cs=tinysrgb&fit=max&fm=jpg&ixid=M3w3NDE5ODJ8MHwxfHNlYXJjaHwxMHx8c3RhbmQlMjBtaXhlcnxlbnwwfHx8fDE3NzEyNDY1OTd8MA&ixlib=rb-4.1.0&q=80&w=1080",
      "imageHint": "stand mixer"
    },
    {
      "id": "registry-item-3",
      "description": "A set of premium luggage",
      "imageUrl": "https://images.unsplash.com/photo-1709010175169-8a22aa4c9598?crop=entropy&cs=tinysrgb&fit=max&fm=jpg&ixid=M3w3NDE5ODJ8MHwxfHNlYXJjaHw1fHxsdWdnYWdlJTIwc2V0fGVufDB8fHx8MTc3MTI0NjU5N3ww&ixlib=rb-4.1.0&q=80&w=1080",
      "imageHint": "luggage set"
    },
    {
      "id": "gallery-1",
      "description": "Guests laughing at a table.",
      "imageUrl": "https://images.unsplash.com/photo-1561928070-590b9c48f0bb?crop=entropy&cs=tinysrgb&fit=max&fm=jpg&ixid=M3w3NDE5ODJ8MHwxfHNlYXJjaHw2fHx3ZWRkaW5nJTIwZ3Vlc3RzfGVufDB8fHx8MTc3MjU3MzIwOHww&ixlib=rb-4.1.0&q=80&w=1080",
      "imageHint": "wedding guests"
    },
    {
      "id": "gallery-2",
      "description": "A closeup of the wedding cake.",
      "imageUrl": "https://picsum.photos/seed/gallery2/600/700",
      "imageHint": "wedding cake"
    },
    {
      "id": "gallery-3",
      "description": "Couple dancing.",
      "imageUrl": "https://picsum.photos/seed/gallery3/600/900",
      "imageHint": "couple dancing"
    },
    {
      "id": "gallery-4",
      "description": "A selfie of two guests.",
      "imageUrl": "https://picsum.photos/seed/gallery4/600/600",
      "imageHint": "friends selfie"
    },
    {
      "id": "gallery-5",
      "description": "A shot of the floral decorations.",
      "imageUrl": "https://picsum.photos/seed/gallery5/600/850",
      "imageHint": "flower decoration"
    },
    {
      "id": "gallery-6",
      "description": "The groom smiling.",
      "imageUrl": "https://picsum.photos/seed/gallery6/600/750",
      "imageHint": "groom smiling"
    },
    {
      "id": "gallery-7",
      "description": "Children playing at the reception.",
      "imageUrl": "https://images.unsplash.com/photo-1621354598022-16599af1b8b2?crop=entropy&cs=tinysrgb&fit=max&fm=jpg&ixid=M3w3NDE5ODJ8MHwxfHNlYXJjaHw0fHxjaGlsZHJlbiUyMHBsYXlpbmd8ZW58MHx8fHwxNzcyNTIxMDc3fDA&ixlib=rb-4.1.0&q=80&w=1080",
      "imageHint": "children playing"
    },
    {
      "id": "gallery-8",
      "description": "A beautiful landscape shot of the venue.",
      "imageUrl": "https://picsum.photos/seed/gallery8/800/600",
      "imageHint": "wedding venue"
    },
    {
      "id": "gallery-9",
      "description": "A guest recording a video message.",
      "imageUrl": "https://picsum.photos/seed/gallery9/600/800",
      "imageHint": "guest phone"
    },
    {
      "id": "gallery-10",
      "description": "A group photo on the dance floor.",
      "imageUrl": "https://picsum.photos/seed/gallery10/700/600",
      "imageHint": "group photo"
    },
    {
      "id": "gallery-11",
      "description": "Candid shot of the bride.",
      "imageUrl": "https://picsum.photos/seed/gallery11/600/950",
      "imageHint": "bride candid"
    },
    {
      "id": "gallery-12",
      "description": "A toast being made.",
      "imageUrl": "https://picsum.photos/seed/gallery12/600/700",
      "imageHint": "wedding toast"
    }
  ]
}